comms/__init__.py
comms/base.py
comms/list.py
items/__init__.py
items/book.py
items/note.py
items/page.py
tools/__init__.py
tools/clui.py
tools/neat.py
tools/sqls.py
sabot-0.0.0.dist-info/METADATA
sabot-0.0.0.dist-info/WHEEL
sabot-0.0.0.dist-info/entry_points.txt
sabot-0.0.0.dist-info/top_level.txt
sabot-0.0.0.dist-info/RECORD
